wav_ytdw/__init__.py
wav_ytdw/wav_ytdw.py
wav_ytdw-0.0.4.dist-info/METADATA
wav_ytdw-0.0.4.dist-info/WHEEL
wav_ytdw-0.0.4.dist-info/top_level.txt
wav_ytdw-0.0.4.dist-info/RECORD
