Metadata-Version: 2.1
Name: wav-ytdw
Version: 0.0.4
Summary: A basic python script to download audio the web.
Home-page: UNKNOWN
Author: JustCow
Author-email: <justcow@pm.me>
License: UNKNOWN
Keywords: python,download,youtube download,audio,wav,justcow
Platform: UNKNOWN
Classifier: Programming Language :: Python :: 3
Classifier: Operating System :: Unix
Classifier: Operating System :: MacOS :: MacOS X
Classifier: Operating System :: Microsoft :: Windows
Requires-Dist: ffmpeg-python
Requires-Dist: youtube-dl
